[
  {
    "id": "arai-motorsports-lightweight-crank-pulley",
    "title": "Arai Motorsports  Lightweight Crank Pulley",
    "brand": "Arai Motorsports",
    "price": 140,
    "original_price": null,
    "compatibility": "Subari EJ",
    "description": "Discontinued / Hard to find\nOEM: 2,500g  \nArai: 700g  \n→ Faster engine response\n✔ Improved throttle response  \n✔ Faster revving  \n✔ Reduced rotational mass  \nPerfect for EJ engine builds",
    "category": "engine",
    "make": "subaru",
    "years": [],
    "models": [],
    "stock": "jp",
    "badge": "JDM",
    "featured": true,
    "image": "/images/uploads/658283638_17933564736206996_9098043188607399842_n.jpg",
    "images": [
      "/images/uploads/657251996_17933564739206996_3986109974747347221_n.jpg",
      "/images/uploads/657712792_17933564760206996_903867128947288842_n.jpg"
    ],
    "emoji": "⚙️"
  },
  {
    "id": "large-overhead-console",
    "title": "Large Overhead Console",
    "brand": "Subaru (OEM)",
    "price": 115,
    "original_price": null,
    "compatibility": "Subaru Legacy BP  2003-2009",
    "description": "Not standard equipment \nHard to find\n✔ Extra storage  \n✔ Clean interior upgrade  \n✔ Genuine Subaru quality",
    "category": "interior",
    "make": "subaru",
    "years": [
      2003
    ],
    "models": [
      "Legacy BP"
    ],
    "stock": "jp",
    "badge": "JDM",
    "featured": true,
    "image": "/images/uploads/658121137_17933562333206996_4737998185613409049_n.jpg",
    "images": [
      "/images/uploads/658428831_17933562330206996_2297405977359023707_n.jpg"
    ],
    "emoji": "🪑"
  },
  {
    "id": "liberal-led-welcome-light-kit",
    "title": "Liberal LED welcome light kit",
    "brand": "Subaru",
    "price": 136,
    "original_price": null,
    "compatibility": "Legacy(Liberty) BP/BL 2006-2009 Impreza GR GV GH 2008-2014 Exiga",
    "description": "Real carbon outside mirror cover\nUsed item, has some scratches, please check the photos.",
    "category": "body",
    "make": "subaru",
    "years": [
      2006,
      2007,
      2008,
      2009
    ],
    "models": [
      "Legacy",
      "Impreza",
      "Exiga"
    ],
    "stock": "jp",
    "badge": "JDM",
    "featured": true,
    "image": "/images/uploads/625329048_17926520121206996_5368252599007464776_n.jpg",
    "images": [
      "/images/uploads/623651762_17926520139206996_3884784124801809566_n.jpg"
    ],
    "emoji": "🚗"
  },
  {
    "id": "real-carbon-hand-brake",
    "title": "Real Carbon Hand Brake",
    "brand": "Subaru",
    "price": 53,
    "original_price": null,
    "compatibility": "Legacy/Liberty 2003-2009 Impreza 2008-2014",
    "description": "",
    "category": "interior",
    "make": "subaru",
    "years": [
      2003,
      2004,
      2005,
      2006
    ],
    "models": [
      "Legacy"
    ],
    "stock": "jp",
    "badge": "JDM",
    "featured": true,
    "image": "/images/uploads/642851105_17930000694206996_6164986669497376250_n.jpg",
    "images": [
      "/images/uploads/640386288_17930000682206996_2476747722662166179_n.jpg"
    ],
    "emoji": "🪑"
  },
  {
    "id": "subaru-genuine-grille",
    "title": "Subaru Genuine Grille",
    "brand": "Subaru",
    "price": 97,
    "original_price": null,
    "compatibility": "Subaru Legacy BP BL 2003-2005 Spec B 2006-2009",
    "description": "",
    "category": "body",
    "make": "subaru",
    "years": [
      2006,
      2007,
      2008,
      2009
    ],
    "models": [
      "Legacy"
    ],
    "stock": "jp",
    "badge": "JDM",
    "featured": true,
    "image": "/images/uploads/652763644_17932032726206996_1949454628986809107_n.jpg",
    "images": [
      "/images/uploads/652052240_17932032735206996_6132884713891134637_n.jpg"
    ],
    "emoji": "🚗"
  }
]